README.md
setup.py
mcheck/__init__.py
mcheck/cmd_call.py
mcheck/constants.py
mcheck/main.py
mcheck/utils.py
mcheck/config/__init__.py
mcheck/config/mars_config.py
mcheck/functions/__init__.py
mcheck/functions/check.py
mcheck/functions/compare.py
mcheck/functions/log.py
mcheck/functions/show.py
mcheck/functions/snap_data.py
mcheck/functions/trace.py
mcheck/lib/__init__.py
mcheck/lib/color.py
mcheck/lib/command_selector.py
mcheck/lib/command_single_selector.py
mcheck/lib/printer.py
mcheck/model/__init__.py
mcheck/model/flow_path.py
mcheck/resource/__init__.py
mcheck/resource/device_configs.py
mcheck/resource/devices.py
mcheck/resource/flows.py
mcheck/resource/groups.py
mcheck/resource/hosts.py
mcheck/resource/links.py
mcheck/resource/resource.py
nocsys_mars_debugtool.egg-info/PKG-INFO
nocsys_mars_debugtool.egg-info/SOURCES.txt
nocsys_mars_debugtool.egg-info/dependency_links.txt
nocsys_mars_debugtool.egg-info/requires.txt
nocsys_mars_debugtool.egg-info/top_level.txt
script/__init__.py
script/mcheck