Metadata-Version: 1.2
Name: nocsys-mars-debugtool
Version: 1.0.1
Summary: A debug tool for debuging the Nocsys Mars Controller controlled fabric and controller itself
Home-page: https://github.com/longshengwang/mars_check
Author: Nocsys
Author-email: longsheng.wang@nocsys.com.cn
License: GNU
Keywords: mars debugtool
Platform: UNKNOWN
Requires-Python: ==2.7.*
